subsequences/__init__.py
subsequences/subsequences.cp38-win_amd64.pyd
subsequences/subsequences.pxd
subsequences/subsequences.py
subsequences/substrings.cp38-win_amd64.pyd
subsequences/substrings.pxd
subsequences/substrings.py
subsequences-0.1.2.dist-info/LICENSE
subsequences-0.1.2.dist-info/WHEEL
subsequences-0.1.2.dist-info/METADATA
subsequences-0.1.2.dist-info/RECORD
