Metadata-Version: 2.1
Name: subsequences
Version: 0.1.2
Summary: Tools for checking for subsequences and substrings
Author: Davis Kirkendall
Author-email: davis.e.kirkendall@gmail.com
Requires-Python: >=3.8,<4.0
Classifier: Programming Language :: Python :: 3
Classifier: Programming Language :: Python :: 3.8
Classifier: Programming Language :: Python :: 3.9
